README.rst
relay.py
setup.py
relay.egg-info/PKG-INFO
relay.egg-info/SOURCES.txt
relay.egg-info/dependency_links.txt
relay.egg-info/entry_points.txt
relay.egg-info/requires.txt
relay.egg-info/top_level.txt