Metadata-Version: 1.0
Name: relay
Version: 0.0.8
Summary: Meta-magical SSH tunnels for remote developers behind firewalls.
Home-page: http://blog.apps.npr.org/
Author: Christopher Groskopf
Author-email: staringmonkey@gmail.com
License: MIT
Platform: UNKNOWN
Classifier: Development Status :: 4 - Beta
Classifier: Environment :: Console
Classifier: Intended Audience :: Developers
Classifier: Intended Audience :: End Users/Desktop
Classifier: License :: OSI Approved :: MIT License
Classifier: Natural Language :: English
Classifier: Operating System :: OS Independent
Classifier: Programming Language :: Python
Classifier: Programming Language :: Python :: 2.6
Classifier: Programming Language :: Python :: 2.7
Classifier: Topic :: Utilities
